examples/verilog_designs/mult/mult.v
module mult #(
    parameter WIDTH = 32
)
(
    input   clk,
    input  [WIDTH-1:0] A,
    input  [WIDTH-1:0] B,
    output reg [WIDTH*2-1:0] Y
);

    always @(posedge clk) begin
        Y <= A * B;
    end

endmodule

examples/verilog_designs/mult/mult_tb.v
`timescale 1ns/100ps

module mult_tb;

    localparam WIDTH = 32;

    reg  clk;
    reg [WIDTH-1:0] A;
    reg [WIDTH-1:0] B;
    wire [WIDTH*2-1:0] Y;

    mult #(
        .WIDTH(WIDTH)
    ) uut (
        .clk(clk),
        .A(A),
        .B(B),
        .Y(Y)
    );

    initial begin
        clk = 0; // Initialize clock
    end

    always #5 clk = ~clk; // Toggle clock every 5ns

    initial begin
      $dumpfile("mult.vcd");
      $dumpvars(0, mult_tb);
    end

    initial begin
        // Initialize inputs
        A = 0;
        B = 0;

        // Wait for a couple of cycles
        @(posedge clk);
        @(posedge clk);

        // Test Case 1: Small positive numbers
        A <= 32'd10;
        B <= 32'd20;
        @(posedge clk);
        @(posedge clk);

        // Test Case 2: One operand is zero
        A <= 32'd12345;
        B <= 32'd0;
        @(posedge clk);
        @(posedge clk);

        // Test Case 3: One operand is one
        A <= 32'd1;
        B <= 32'd9876;
        @(posedge clk);
        @(posedge clk);

        // Test Case 4: Larger numbers
        A <= 32'd100000;
        B <= 32'd50000;
        @(posedge clk);
        @(posedge clk);

        // Test Case 5: Maximum value for one input
        A <= 32'hFFFF_FFFF;
        B <= 32'd2;
        @(posedge clk);
        @(posedge clk);

        // Test Case 6: Random values
        A <= $random;
        B <= $random;
        @(posedge clk);
        @(posedge clk);

        #20; // Wait a bit longer
        $finish;
    end

endmodule

examples/verilog_designs/mult/mult.vcd
$date
	Sun Aug  3 16:04:08 2025
$end
$version
	Icarus Verilog
$end
$timescale
	100ps
$end
$scope module mult_tb $end
$var wire 64 ! Y [63:0] $end
$var reg 32 " A [31:0] $end
$var reg 32 # B [31:0] $end
$var reg 1 $ clk $end
$scope module uut $end
$var wire 32 % A [31:0] $end
$var wire 32 & B [31:0] $end
$var wire 1 $ clk $end
$var reg 64 ' Y [63:0] $end
$upscope $end
$upscope $end
$enddefinitions $end
#0
$dumpvars
bx '
b0 &
b0 %
0$
b0 #
b0 "
bx !
$end
#50
b0 !
b0 '
1$
#100
0$
#150
b10100 #
b10100 &
b1010 "
b1010 %
1$
#200
0$
#250
b11001000 !
b11001000 '
1$
#300
0$
#350
b0 #
b0 &
b11000000111001 "
b11000000111001 %
1$
#400
0$
#450
b0 !
b0 '
1$
#500
0$
#550
b10011010010100 #
b10011010010100 &
b1 "
b1 %
1$
#600
0$
#650
b10011010010100 !
b10011010010100 '
1$
#700
0$
#750
b1100001101010000 #
b1100001101010000 &
b11000011010100000 "
b11000011010100000 %
1$
#800
0$
#850
b100101010000001011111001000000000 !
b100101010000001011111001000000000 '
1$
#900
0$
#950
b10 #
b10 &
b11111111111111111111111111111111 "
b11111111111111111111111111111111 %
1$
#1000
0$
#1050
b111111111111111111111111111111110 !
b111111111111111111111111111111110 '
1$
#1100
0$
#1150
b11000000100010010101111010000001 #
b11000000100010010101111010000001 &
b10010000101010011010100100100 "
b10010000101010011010100100100 %
1$
#1200
0$
#1250
b110110011001100110111110000101010110011101101111111100100100 !
b110110011001100110111110000101010110011101101111111100100100 '
1$
